[
	{
		"in-domain": {
			"B1": 68.25,
			"B2": 46.78,
			"B3": 25.95,
			"B4": 13.47,
			"METEOR": 20.58,
			"ROUGE-L": 47.16,
			"CIDEr": 47.3,
			"SPICE": 8.23
		}
	},
	{
		"near-domain": {
			"B1": 64.87,
			"B2": 42.48,
			"B3": 20.98,
			"B4": 9.28,
			"METEOR": 18.06,
			"ROUGE-L": 44.39,
			"CIDEr": 32.61,
			"SPICE": 7.53
		}
	},
	{
		"out-domain": {
			"B1": 57.3,
			"B2": 32.13,
			"B3": 12.82,
			"B4": 3.72,
			"METEOR": 13.97,
			"ROUGE-L": 39.53,
			"CIDEr": 15.35,
			"SPICE": 6.33
		}
	},
	{
		"entire": {
			"B1": 63.82,
			"B2": 41.0,
			"B3": 20.04,
			"B4": 8.76,
			"METEOR": 17.59,
			"ROUGE-L": 43.8,
			"CIDEr": 31.22,
			"SPICE": 7.46
		}
	}
]
